Metadata-Version: 2.1
Name: lupe-mice
Version: 0.0
Summary: Introducing LUPE, the innovative no code website predicting pain behavior in mice.
Home-page: https://github.com/runninghsus/lupe
Author: alexanderhsu
Author-email: ahsu2@andrew.cmu.edu
Requires-Python: >=3.9
Requires-Dist: altair (==5.1.1)
Requires-Dist: anyio (==4.0.0)
Requires-Dist: appnope (==0.1.3)
Requires-Dist: argon2-cffi (==23.1.0)
Requires-Dist: argon2-cffi-bindings (==21.2.0)
Requires-Dist: arrow (==1.2.3)
Requires-Dist: asttokens (==2.4.0)
Requires-Dist: async-lru (==2.0.4)
Requires-Dist: attrs (==23.1.0)
Requires-Dist: Babel (==2.12.1)
Requires-Dist: backcall (==0.2.0)
Requires-Dist: beautifulsoup4 (==4.12.2)
Requires-Dist: bleach (==6.0.0)
Requires-Dist: blinker (==1.6.2)
Requires-Dist: cachetools (==5.3.1)
Requires-Dist: certifi (==2023.7.22)
Requires-Dist: cffi (==1.15.1)
Requires-Dist: charset-normalizer (==3.2.0)
Requires-Dist: click (==8.1.7)
Requires-Dist: comm (==0.1.4)
Requires-Dist: contourpy (==1.1.0)
Requires-Dist: cycler (==0.11.0)
Requires-Dist: debugpy (==1.6.7.post1)
Requires-Dist: decorator (==5.1.1)
Requires-Dist: defusedxml (==0.7.1)
Requires-Dist: docutils (==0.20.1)
Requires-Dist: exceptiongroup (==1.1.3)
Requires-Dist: executing (==1.2.0)
Requires-Dist: extra-streamlit-components (==0.1.60)
Requires-Dist: fastjsonschema (==2.18.0)
Requires-Dist: ffmpeg-python (==0.2.0)
Requires-Dist: fonttools (==4.42.1)
Requires-Dist: fqdn (==1.5.1)
Requires-Dist: future (==0.18.3)
Requires-Dist: gitdb (==4.0.10)
Requires-Dist: GitPython (==3.1.34)
Requires-Dist: idna (==3.4)
Requires-Dist: importlib-metadata (==6.8.0)
Requires-Dist: importlib-resources (==6.0.1)
Requires-Dist: ipykernel (==6.25.2)
Requires-Dist: ipython (==8.15.0)
Requires-Dist: ipython-genutils (==0.2.0)
Requires-Dist: ipywidgets (==8.1.0)
Requires-Dist: isoduration (==20.11.0)
Requires-Dist: jaraco.classes (==3.3.0)
Requires-Dist: jedi (==0.19.0)
Requires-Dist: Jinja2 (==3.1.2)
Requires-Dist: joblib (==1.3.2)
Requires-Dist: json5 (==0.9.14)
Requires-Dist: jsonpointer (==2.4)
Requires-Dist: jsonschema (==4.19.0)
Requires-Dist: jsonschema-specifications (==2023.7.1)
Requires-Dist: jupyter (==1.0.0)
Requires-Dist: jupyter-console (==6.6.3)
Requires-Dist: jupyter-events (==0.7.0)
Requires-Dist: jupyter-lsp (==2.2.0)
Requires-Dist: jupyter-client (==8.3.1)
Requires-Dist: jupyter-core (==5.3.1)
Requires-Dist: jupyter-server (==2.7.3)
Requires-Dist: jupyter-server-terminals (==0.4.4)
Requires-Dist: jupyterlab (==4.0.5)
Requires-Dist: jupyterlab-pygments (==0.2.2)
Requires-Dist: jupyterlab-widgets (==3.0.8)
Requires-Dist: jupyterlab-server (==2.24.0)
Requires-Dist: keyring (==24.2.0)
Requires-Dist: kiwisolver (==1.4.5)
Requires-Dist: llvmlite (==0.40.1)
Requires-Dist: markdown-it-py (==3.0.0)
Requires-Dist: MarkupSafe (==2.1.3)
Requires-Dist: matplotlib (==3.7.2)
Requires-Dist: matplotlib-inline (==0.1.6)
Requires-Dist: mdurl (==0.1.2)
Requires-Dist: mistune (==3.0.1)
Requires-Dist: more-itertools (==10.1.0)
Requires-Dist: nbclient (==0.8.0)
Requires-Dist: nbconvert (==7.8.0)
Requires-Dist: nbformat (==5.9.2)
Requires-Dist: nest-asyncio (==1.5.7)
Requires-Dist: networkx (==3.1)
Requires-Dist: notebook (==7.0.3)
Requires-Dist: notebook-shim (==0.2.3)
Requires-Dist: numba (==0.57.1)
Requires-Dist: numpy (==1.24.4)
Requires-Dist: overrides (==7.4.0)
Requires-Dist: packaging (==23.1)
Requires-Dist: pandas (==2.0.3)
Requires-Dist: pandocfilters (==1.5.0)
Requires-Dist: parso (==0.8.3)
Requires-Dist: pexpect (==4.8.0)
Requires-Dist: pickleshare (==0.7.5)
Requires-Dist: Pillow (==9.5.0)
Requires-Dist: pkginfo (==1.9.6)
Requires-Dist: platformdirs (==3.10.0)
Requires-Dist: plotly (==5.16.1)
Requires-Dist: prometheus-client (==0.17.1)
Requires-Dist: prompt-toolkit (==3.0.39)
Requires-Dist: protobuf (==4.24.2)
Requires-Dist: psutil (==5.9.5)
Requires-Dist: ptyprocess (==0.7.0)
Requires-Dist: pure-eval (==0.2.2)
Requires-Dist: pyarrow (==13.0.0)
Requires-Dist: pycparser (==2.21)
Requires-Dist: pydeck (==0.8.0)
Requires-Dist: Pygments (==2.16.1)
Requires-Dist: Pympler (==1.0.1)
Requires-Dist: pyparsing (==3.0.9)
Requires-Dist: python-dateutil (==2.8.2)
Requires-Dist: python-json-logger (==2.0.7)
Requires-Dist: pytz (==2023.3.post1)
Requires-Dist: pytz-deprecation-shim (==0.1.0.post0)
Requires-Dist: PyYAML (==6.0.1)
Requires-Dist: pyzmq (==25.1.1)
Requires-Dist: qtconsole (==5.4.4)
Requires-Dist: QtPy (==2.4.0)
Requires-Dist: readme-renderer (==41.0)
Requires-Dist: referencing (==0.30.2)
Requires-Dist: requests (==2.31.0)
Requires-Dist: requests-toolbelt (==1.0.0)
Requires-Dist: rfc3339-validator (==0.1.4)
Requires-Dist: rfc3986 (==2.0.0)
Requires-Dist: rfc3986-validator (==0.1.1)
Requires-Dist: rich (==13.5.2)
Requires-Dist: rpds-py (==0.10.2)
Requires-Dist: scikit-learn (==1.2.1)
Requires-Dist: scipy (==1.11.2)
Requires-Dist: seaborn (==0.12.2)
Requires-Dist: Send2Trash (==1.8.2)
Requires-Dist: six (==1.16.0)
Requires-Dist: smmap (==5.0.0)
Requires-Dist: sniffio (==1.3.0)
Requires-Dist: soupsieve (==2.5)
Requires-Dist: stack-data (==0.6.2)
Requires-Dist: stqdm (==0.0.5)
Requires-Dist: streamlit (==1.26.0)
Requires-Dist: streamlit-option-menu (==0.3.6)
Requires-Dist: tenacity (==8.2.3)
Requires-Dist: terminado (==0.17.1)
Requires-Dist: threadpoolctl (==3.2.0)
Requires-Dist: tinycss2 (==1.2.1)
Requires-Dist: toml (==0.10.2)
Requires-Dist: tomli (==2.0.1)
Requires-Dist: toolz (==0.12.0)
Requires-Dist: tornado (==6.3.3)
Requires-Dist: tqdm (==4.66.1)
Requires-Dist: traitlets (==5.9.0)
Requires-Dist: twine (==4.0.2)
Requires-Dist: typing-extensions (==4.7.1)
Requires-Dist: tzdata (==2023.3)
Requires-Dist: tzlocal (==4.3.1)
Requires-Dist: uri-template (==1.3.0)
Requires-Dist: urllib3 (==2.0.4)
Requires-Dist: validators (==0.22.0)
Requires-Dist: watchdog (==3.0.0)
Requires-Dist: wcwidth (==0.2.6)
Requires-Dist: webcolors (==1.13)
Requires-Dist: webencodings (==0.5.1)
Requires-Dist: websocket-client (==1.6.2)
Requires-Dist: widgetsnbextension (==4.0.8)
Requires-Dist: zipp (==3.16.2)
